README.rst
setup.py
shakedown/__init__.py
shakedown/__version__.py
shakedown/cleanups.py
shakedown/conf.py
shakedown/ctx.py
shakedown/exception_handling.py
shakedown/exceptions.py
shakedown/hooks.py
shakedown/interfaces.py
shakedown/loader.py
shakedown/local.py
shakedown/log.py
shakedown/metadata.py
shakedown/parameters.py
shakedown/result.py
shakedown/runnable_test.py
shakedown/runnable_test_factory.py
shakedown/runner.py
shakedown/session.py
shakedown/should.py
shakedown/site.py
shakedown/test.py
shakedown.egg-info/PKG-INFO
shakedown.egg-info/SOURCES.txt
shakedown.egg-info/dependency_links.txt
shakedown.egg-info/entry_points.txt
shakedown.egg-info/requires.txt
shakedown.egg-info/top_level.txt
shakedown/frontend/__init__.py
shakedown/frontend/main.py
shakedown/frontend/shake_run.py
shakedown/plugins/__init__.py
shakedown/plugins/interface.py
shakedown/plugins/builtin/__init__.py
shakedown/plugins/builtin/notifications.py
shakedown/utils/__init__.py
shakedown/utils/callback.py
shakedown/utils/cli_utils.py
shakedown/utils/conf_utils.py
shakedown/utils/debug.py
shakedown/utils/formatter.py
shakedown/utils/id_space.py
shakedown/utils/imports.py
shakedown/utils/interactive.py
shakedown/utils/operator_information.py
shakedown/utils/path.py
shakedown/utils/reporter.py
tests/utils/__init__.py
tests/utils/test_generator.py